geopins/__init__.py
geopins/_version.py
geopins/boards.py
geopins/filetypes.py
geopins/interfaces.py
geopins/meta.py
geopins/patch_.py
geopins/drivers/__init__.py
geopins/drivers/exceptions.py
geopins/drivers/infer.py
geopins/drivers/gdf/__init__.py
geopins/drivers/gdf/dispatch.py
geopins/drivers/gdf/filetypes/__init__.py
geopins/drivers/gdf/filetypes/gpkg.py
geopins/drivers/gdf/filetypes/parquet.py
geopins/drivers/raster/__init__.py
geopins/drivers/raster/dispatch.py
geopins/drivers/raster/filetypes/__init__.py
geopins/drivers/raster/filetypes/tif.py
geopins-0.1.1.dist-info/METADATA
geopins-0.1.1.dist-info/WHEEL
geopins-0.1.1.dist-info/licenses/LICENSE
geopins-0.1.1.dist-info/RECORD
