Metadata-Version: 2.4
Name: geopins
Version: 0.1.1
Summary: Geospatial support for the Python pins package.
Project-URL: Source Code, https://github.com/tonkintaylor/geopins
Project-URL: Bug Tracker, https://github.com/tonkintaylor/geopins/issues
Project-URL: Releases, https://github.com/tonkintaylor/geopins/releases
Project-URL: Source Archive, https://github.com/tonkintaylor/geopins/archive/6fc84ae864c73b16bc8d0ee3ebbb7fd3be5c1974.zip
Author-email: Tonkin & Taylor Limited <Sub-DisciplineData+AnalyticsStaff@tonkintaylor.co.nz>, Nathan McDougall <nmcdougall@tonkintaylor.co.nz>, Ben Karl <bkarl@tonkintaylor.co.nz>
License-Expression: MIT
License-File: LICENSE
Classifier: Programming Language :: Python :: 3 :: Only
Classifier: Programming Language :: Python :: 3.10
Classifier: Programming Language :: Python :: 3.11
Classifier: Programming Language :: Python :: 3.12
Classifier: Programming Language :: Python :: 3.13
Requires-Python: >=3.10
Requires-Dist: geopandas>=1.1.1
Requires-Dist: pins>=0.9.1
Requires-Dist: pyarrow>=21.0.0
Requires-Dist: rastr>=0.6.0
